rtl/data_memory.v
`timescale 1ns / 1ps

// DATA MEMORY
// 256 x 32-bit word-addressable memory
// Synchronous write, asynchronous read

module data_memory(
    input         clk,
    input         rst,
    input  [31:0] addr,       // byte address (word aligned)
    input  [31:0] wr_data,    // data to write
    input         sw,         // store enable
    output [31:0] rd_data     // data read output
);

    reg [31:0] mem [0:255];   // 256 words, 32-bit wide (fixed from 8-bit)
    integer i;

    // Synchronous write
    always @(posedge clk) begin
        if (rst) begin
            for (i = 0; i < 256; i = i + 1)
                mem[i] <= 32'b0;
        end else if (sw) begin
            mem[addr[9:2]] <= wr_data;   // word-aligned: divide addr by 4
        end
    end

    // Asynchronous read
    assign rd_data = mem[addr[9:2]];

endmodule

rtl/alu.v
`timescale 1ns / 1ps


// Supports all RV32I arithmetic, logic, shift, and branch compare operations

module alu(
    input  [31:0] src1,         // register rs1 value
    input  [31:0] src2,         // register rs2 value OR immediate
    input  [5:0]  alu_control,  // operation select
    output reg [31:0] result
);

    always @(*) begin
        case (alu_control)

        
            // R-TYPE OPERATIONS
           
            6'b000001: result = src1 + src2;                                        // ADD
            6'b000010: result = src1 - src2;                                        // SUB
            6'b000011: result = src1 << src2[4:0];                                  // SLL
            6'b000100: result = ($signed(src1) < $signed(src2)) ? 32'd1 : 32'd0;   // SLT
            6'b000101: result = ($unsigned(src1) < $unsigned(src2)) ? 32'd1 : 32'd0; // SLTU
            6'b000110: result = src1 ^ src2;                                        // XOR
            6'b000111: result = src1 >> src2[4:0];                                  // SRL
            6'b001000: result = $signed(src1) >>> src2[4:0];                        // SRA
            6'b001001: result = src1 | src2;                                        // OR
            6'b001010: result = src1 & src2;                                        // AND

          
            // I-TYPE OPERATIONS (immediate in src2)
           
            6'b001011: result = src1 + src2;                                        // ADDI
            6'b001100: result = src1 << src2[4:0];                                  // SLLI
            6'b001101: result = ($signed(src1) < $signed(src2)) ? 32'd1 : 32'd0;   // SLTI
            6'b001110: result = ($unsigned(src1) < $unsigned(src2)) ? 32'd1 : 32'd0; // SLTIU
            6'b001111: result = src1 ^ src2;                                        // XORI
            6'b010000: result = src1 >> src2[4:0];                                  // SRLI
            6'b010001: result = $signed(src1) >>> src2[4:0];                        // SRAI
            6'b010010: result = src1 | src2;                                        // ORI
            6'b010011: result = src1 & src2;                                        // ANDI

        
            // LOAD / STORE 
           
            6'b010100: result = src1 + src2;                                        // LB  address
            6'b010101: result = src1 + src2;                                        // LH  address
            6'b010110: result = src1 + src2;                                        // LW  address
            6'b010111: result = src1 + src2;                                        // LBU address
            6'b011000: result = src1 + src2;                                        // LHU address
            6'b011001: result = src1 + src2;                                        // SW  address
            6'b011010: result = src1 + src2;                                        // SH  address
            6'b011011: result = src1 + src2;                                        // SB  address

         
            // BRANCH COMPARE
            
            6'b011100: result = (src1 == src2) ? 32'd1 : 32'd0;                    // BEQ
            6'b011101: result = (src1 != src2) ? 32'd1 : 32'd0;                    // BNE
            6'b011110: result = ($signed(src1) < $signed(src2)) ? 32'd1 : 32'd0;   // BLT
            6'b011111: result = ($signed(src1) >= $signed(src2)) ? 32'd1 : 32'd0;  // BGE
            6'b100000: result = ($unsigned(src1) < $unsigned(src2)) ? 32'd1 : 32'd0; // BLTU
            6'b100001: result = ($unsigned(src1) >= $unsigned(src2)) ? 32'd1 : 32'd0; // BGEU

           
            // LUI / JAL 
           
            6'b100010: result = src2;                                               // LUI
            6'b100011: result = src1 + src2;                                        // JAL/JALR address

            default:   result = 32'b0;
        endcase
    end

endmodule

rtl/register_file.v
`timescale 1ns / 1ps

// REGISTER FILE  
// Write on NEGEDGE, Read (asynchronous)
// This allows: write in first half of cycle, read updated value in second half
// Eliminates RAW hazard in single-cycle design without forwarding loops
// x0 hardwired to 0

module register_file(
    input         clk,
    input         rst,
    input  [4:0]  rs1,
    input  [4:0]  rs2,
    input  [4:0]  rd,
    input  [31:0] write_data,
    input         reg_write,
    output [31:0] read_data1,
    output [31:0] read_data2
);

    reg [31:0] regs [0:31];
    integer i;

    // Write on NEGEDGE — first half of clock cycle
    always @(negedge clk) begin
        if (rst) begin
            for (i = 0; i < 32; i = i + 1)
                regs[i] <= 32'b0;
        end else if (reg_write && rd != 5'b0) begin
            regs[rd] <= write_data;
        end
    end

    // Asynchronous read — sees negedge-written value
    assign read_data1 = (rs1 == 5'b0) ? 32'b0 : regs[rs1];
    assign read_data2 = (rs2 == 5'b0) ? 32'b0 : regs[rs2];

endmodule

rtl/data_path.v
`timescale 1ns / 1ps

// DATAPATH
// Connects: Register File, ALU, Data Memory, Immediate Gen

module data_path(
    input         clk,
    input         rst,
    input  [4:0]  rs1,
    input  [4:0]  rs2,
    input  [4:0]  rd,
    input  [5:0]  alu_control,
    input         jump,
    input         beq_control,
    input         bneq_control,
    input         bgeq_control,
    input         blt_control,
    input         mem_to_reg,
    input         lb,
    input         sw,
    input         lui_control,
    input         reg_write,
    input  [31:0] imm_val,
    input  [31:0] pc_plus4,
    output        beq,
    output        bneq,
    output        bge,
    output        blt,
    output [31:0] alu_result   // exposed for debug
);

    wire [31:0] read_data1;
    wire [31:0] read_data2;
    wire [31:0] mem_rd_data;
    wire [31:0] alu_src2;
    wire [31:0] write_back_data;

    // ALU src2 mux — carefully separated by instruction type:
    // R-type    (6'b000001–6'b001010): compare/compute reg vs reg → read_data2
    // I-type    (6'b001011–6'b010011): ALU with immediate         → imm_val
    // Load/Store(6'b010100–6'b011011): address = base + offset    → imm_val
    // Branch    (6'b011100–6'b100001): compare rs1 vs rs2         → read_data2
    // LUI/JAL   (6'b100010–6'b100011): pass immediate through     → imm_val
    assign alu_src2 = ((alu_control >= 6'b000001 && alu_control <= 6'b001010) ||
                       (alu_control >= 6'b011100 && alu_control <= 6'b100001))
                       ? read_data2 : imm_val;

    // Write-back mux
    assign write_back_data = jump       ? pc_plus4   :
                             mem_to_reg ? mem_rd_data :
                                          alu_result;

    // Register File
    register_file rf (
        .clk        (clk),
        .rst        (rst),
        .rs1        (rs1),
        .rs2        (rs2),
        .rd         (rd),
        .write_data (write_back_data),
        .reg_write  (reg_write),
        .read_data1 (read_data1),
        .read_data2 (read_data2)
    );

    // ALU
    alu alu_unit (
        .src1        (read_data1),
        .src2        (alu_src2),
        .alu_control (alu_control),
        .result      (alu_result)
    );

    // Data Memory
    data_memory dmem (
        .clk     (clk),
        .rst     (rst),
        .addr    (alu_result),
        .wr_data (read_data2),
        .sw      (sw),
        .rd_data (mem_rd_data)
    );

    // Branch signals → IFU
    assign beq  = (alu_result == 32'd1 && beq_control)  ? 1'b1 : 1'b0;
    assign bneq = (alu_result == 32'd1 && bneq_control) ? 1'b1 : 1'b0;
    assign bge  = (alu_result == 32'd1 && bgeq_control) ? 1'b1 : 1'b0;
    assign blt  = (alu_result == 32'd1 && blt_control)  ? 1'b1 : 1'b0;

endmodule

rtl/imm_gen.v
`timescale 1ns / 1ps

// IMMEDIATE GENERATOR
// Extracts and sign-extends immediate values for all RV32I instruction types

module imm_gen(
    input  [31:0] instr,        // full 32-bit instruction
    output reg [31:0] imm_out   // sign-extended immediate value
);

    wire [6:0] opcode;
    assign opcode = instr[6:0];

    always @(*) begin
        case (opcode)

            // I-type: ADDI, SLTI, XORI, ORI, ANDI, SLLI, SRLI, SRAI
            7'b0010011,
            // I-type: LB, LH, LW, LBU, LHU
            7'b0000011,
            // I-type: JALR
            7'b1100111:
                imm_out = {{20{instr[31]}}, instr[31:20]};

            // S-type: SW, SH, SB
            7'b0100011:
                imm_out = {{20{instr[31]}}, instr[31:25], instr[11:7]};

            // B-type: BEQ, BNE, BLT, BGE, BLTU, BGEU
            7'b1100011:
                imm_out = {{20{instr[31]}}, instr[7], instr[30:25], instr[11:8], 1'b0};

            // U-type: LUI
            7'b0110111,
            // U-type: AUIPC
            7'b0010111:
                imm_out = {instr[31:12], 12'b0};

            // J-type: JAL
            7'b1101111:
                imm_out = {{12{instr[31]}}, instr[19:12], instr[20], instr[30:21], 1'b0};

            default:
                imm_out = 32'b0;
        endcase
    end

endmodule

rtl/control_unit.v
`timescale 1ns / 1ps

// Decodes opcode + funct3 + funct7 and drives all control signals

module control_unit(
    input        reset,
    input  [6:0] funct7,
    input  [2:0] funct3,
    input  [6:0] opcode,
    output reg [5:0] alu_control,
    output reg       lb,
    output reg       mem_to_reg,
    output reg       bneq_control,
    output reg       beq_control,
    output reg       bgeq_control,
    output reg       blt_control,
    output reg       jump,
    output reg       sw,
    output reg       lui_control,
    output reg       reg_write       //  enables register file write
);

    always @(*) begin

        // Default all signals to 0 — prevents latches
        alu_control  = 6'b0;
        lb           = 0;
        mem_to_reg   = 0;
        beq_control  = 0;
        bneq_control = 0;
        bgeq_control = 0;
        blt_control  = 0;
        jump         = 0;
        sw           = 0;
        lui_control  = 0;
        reg_write    = 0;

        if (reset) begin
           
        end else begin

            case (opcode)

               
                // R-TYPE
                
                7'b0110011: begin
                    reg_write = 1;
                    case (funct3)
                        3'b000: alu_control = (funct7 == 7'b0100000) ? 6'b000010 : 6'b000001; // SUB : ADD
                        3'b001: alu_control = 6'b000011; // SLL
                        3'b010: alu_control = 6'b000100; // SLT
                        3'b011: alu_control = 6'b000101; // SLTU
                        3'b100: alu_control = 6'b000110; // XOR
                        3'b101: alu_control = (funct7 == 7'b0100000) ? 6'b001000 : 6'b000111; // SRA : SRL
                        3'b110: alu_control = 6'b001001; // OR
                        3'b111: alu_control = 6'b001010; // AND
                        default: alu_control = 6'b0;
                    endcase
                end

            
                // I-TYPE ALU
                
                7'b0010011: begin
                    reg_write = 1;
                    case (funct3)
                        3'b000: alu_control = 6'b001011; // ADDI
                        3'b001: alu_control = 6'b001100; // SLLI
                        3'b010: alu_control = 6'b001101; // SLTI
                        3'b011: alu_control = 6'b001110; // SLTIU
                        3'b100: alu_control = 6'b001111; // XORI
                        3'b101: alu_control = (funct7 == 7'b0100000) ? 6'b010001 : 6'b010000; // SRAI : SRLI
                        3'b110: alu_control = 6'b010010; // ORI
                        3'b111: alu_control = 6'b010011; // ANDI
                        default: alu_control = 6'b0;
                    endcase
                end

        
                // LOAD
               
                7'b0000011: begin
                    mem_to_reg = 1;
                    reg_write  = 1;
                    lb         = 1;
                    case (funct3)
                        3'b000: alu_control = 6'b010100; // LB
                        3'b001: alu_control = 6'b010101; // LH
                        3'b010: alu_control = 6'b010110; // LW
                        3'b100: alu_control = 6'b010111; // LBU
                        3'b101: alu_control = 6'b011000; // LHU
                        default: alu_control = 6'b0;
                    endcase
                end

                
                // STORE
              
                7'b0100011: begin
                    sw = 1;
                    case (funct3)
                        3'b000: alu_control = 6'b011011; // SB
                        3'b001: alu_control = 6'b011010; // SH
                        3'b010: alu_control = 6'b011001; // SW
                        default: alu_control = 6'b0;
                    endcase
                end

               
                // BRANCH
                
                7'b1100011: begin
                    case (funct3)
                        3'b000: begin alu_control = 6'b011100; beq_control  = 1; end // BEQ
                        3'b001: begin alu_control = 6'b011101; bneq_control = 1; end // BNE
                        3'b100: begin alu_control = 6'b011110; blt_control  = 1; end // BLT
                        3'b101: begin alu_control = 6'b011111; bgeq_control = 1; end // BGE
                        3'b110: begin alu_control = 6'b100000; blt_control  = 1; end // BLTU
                        3'b111: begin alu_control = 6'b100001; bgeq_control = 1; end // BGEU
                        default: alu_control = 6'b0;
                    endcase
                end

              
                // LUI
                
                7'b0110111: begin
                    alu_control = 6'b100010;
                    lui_control = 1;
                    reg_write   = 1;
                end

       
                // JAL
               
                7'b1101111: begin
                    alu_control = 6'b100011;
                    jump        = 1;
                    reg_write   = 1;
                end

                
                // JALR
               
                7'b1100111: begin
                    alu_control = 6'b100011;
                    jump        = 1;
                    reg_write   = 1;
                end

                default: alu_control = 6'b0;

            endcase
        end
    end

endmodule

rtl/INSTRUCTION_MEMORY_fibo.v
`timescale 1ns / 1ps

// INSTRUCTION MEMORY — Fibonacci Program (no NOPs needed)
// x1 = 21 (fib[8]), x2 = 34 (fib[9]) after execution

module instruction_memory(
    input  [31:0] pc,
    output [31:0] instruction
);

    reg [31:0] mem [0:255];

    initial begin
        mem[0]  = 32'h00000093; // ADDI x1,  x0, 0    → x1=0
        mem[1]  = 32'h00100113; // ADDI x2,  x0, 1    → x2=1
        mem[2]  = 32'h00800513; // ADDI x10, x0, 8    → counter=8
        // loop at PC=0x0C
        mem[3]  = 32'h002081B3; // ADD  x3, x1, x2    → x3=x1+x2
        mem[4]  = 32'h00010093; // ADDI x1, x2, 0     → x1=x2
        mem[5]  = 32'h00018113; // ADDI x2, x3, 0     → x2=x3
        mem[6]  = 32'hFFF50513; // ADDI x10,x10,-1    → counter--
        // BNE x10, x0, -16 (back to mem[3] = PC=0x0C)
        // BNE at PC=0x1C, target=0x0C, offset=-16
        mem[7]  = 32'hFE0518E3; // BNE x10, x0, -16
        mem[8]  = 32'h00000013; // NOP
        mem[9]  = 32'h00000013; // NOP

        begin : fill
            integer i;
            for (i = 10; i < 256; i = i + 1)
                mem[i] = 32'h00000013;
        end
    end

    assign instruction = mem[pc[9:2]];

endmodule

rtl/instruction_fetch_unit.v
`timescale 1ns / 1ps

// INSTRUCTION FETCH UNIT
// Manages the Program Counter
// Handles: normal increment, branch, jump

module instruction_fetch_unit(
    input         clk,
    input         reset,
    input  [31:0] imm_branch,    // branch offset (from imm_gen)
    input  [31:0] imm_jump,      // jump offset (from imm_gen)
    input         beq,           // branch taken signal
    input         bneq,
    input         bge,
    input         blt,
    input         jump,
    output reg [31:0] pc,        // current program counter
    output reg [31:0] pc_plus4   // return address for JAL
);

    always @(posedge clk) begin
        if (reset) begin
            pc       <= 32'b0;
            pc_plus4 <= 32'b0;
        end else begin
            pc_plus4 <= pc + 4;   // always save return address

            if (jump)
                pc <= pc + imm_jump;                              // JAL: PC-relative
            else if (beq || bneq || bge || blt)
                pc <= pc + imm_branch;                            // branch: PC-relative
            else
                pc <= pc + 4;                                     // normal increment
        end
    end

endmodule

rtl/top_riscv.v
`timescale 1ns / 1ps

module top_riscv(
    input clk,
    input reset
);

    wire [31:0] pc, pc_plus4, instruction, imm_val;
    wire [5:0]  alu_control;
    wire        mem_to_reg, beq_control, bneq_control;
    wire        bgeq_control, blt_control, jump, sw, lb, lui_control, reg_write;
    wire        beq, bneq, bge, blt;

    instruction_fetch_unit ifu (
        .clk        (clk),   .reset      (reset),
        .imm_branch (imm_val),.imm_jump   (imm_val),
        .beq        (beq),   .bneq       (bneq),
        .bge        (bge),   .blt        (blt),
        .jump       (jump),  .pc         (pc),
        .pc_plus4   (pc_plus4)
    );

    instruction_memory imem (
        .pc          (pc),
        .instruction (instruction)
    );

    control_unit cu (
        .reset       (reset),
        .funct7      (instruction[31:25]),
        .funct3      (instruction[14:12]),
        .opcode      (instruction[6:0]),
        .alu_control (alu_control),
        .lb          (lb),         .mem_to_reg  (mem_to_reg),
        .bneq_control(bneq_control),.beq_control (beq_control),
        .bgeq_control(bgeq_control),.blt_control (blt_control),
        .jump        (jump),       .sw          (sw),
        .lui_control (lui_control),.reg_write   (reg_write)
    );

    imm_gen ig (
        .instr   (instruction),
        .imm_out (imm_val)
    );

    data_path dpu (
        .clk          (clk),          .rst          (reset),
        .rs1          (instruction[19:15]),
        .rs2          (instruction[24:20]),
        .rd           (instruction[11:7]),
        .alu_control  (alu_control),  .jump         (jump),
        .beq_control  (beq_control),  .bneq_control (bneq_control),
        .bgeq_control (bgeq_control), .blt_control  (blt_control),
        .mem_to_reg   (mem_to_reg),   .lb           (lb),
        .sw           (sw),           .lui_control  (lui_control),
        .reg_write    (reg_write),    .imm_val      (imm_val),
        .pc_plus4     (pc_plus4),
        .beq          (beq),          .bneq         (bneq),
        .bge          (bge),          .blt          (blt),
        .alu_result   ()
    );

endmodule

tb/tb_fibonacci.v
`timescale 1ns / 1ps

module tb_fibonacci;

    reg clk, reset;
    top_riscv dut (.clk(clk), .reset(reset));

    initial clk = 0;
    always #5 clk = ~clk;

  initial begin
    $dumpfile("fibonacci_wave.vcd");
    $dumpvars(0, tb_fibonacci);
    // Force dump all register array elements
    $dumpvars(0, tb_fibonacci.dut.dpu.rf.regs[0]);
    $dumpvars(0, tb_fibonacci.dut.dpu.rf.regs[1]);
    $dumpvars(0, tb_fibonacci.dut.dpu.rf.regs[2]);
    $dumpvars(0, tb_fibonacci.dut.dpu.rf.regs[3]);
    $dumpvars(0, tb_fibonacci.dut.dpu.rf.regs[10]);
end

    // Watch PC and key registers every cycle
    initial begin
        $display("Cycle |  PC  | x1(fib) | x2(fib) | x10(ctr)");
        $display("------+------+---------+---------+---------");
    end

    always @(posedge clk) begin
        if (!reset)
        $display("%5t | %4h | %7d | %7d | %7d",
            $time,
            dut.pc,
            dut.dpu.rf.regs[1],
            dut.dpu.rf.regs[2],
            dut.dpu.rf.regs[10]);
    end

    initial begin
        reset = 1;
        repeat(2) @(posedge clk); #1;
        reset = 0;

        // Run enough cycles for 8 loop iterations
        // Each iteration = 5 instructions + branch = ~6 cycles
        // 8 iterations * 6 + setup = ~55 cycles
        repeat(60) @(posedge clk); #1;

        $display("================================================");
        $display("  FIBONACCI RESULT");
        $display("================================================");
        $display("  x1  = %0d  (expect 21 = fib[8])", dut.dpu.rf.regs[1]);
        $display("  x2  = %0d  (expect 34 = fib[9])", dut.dpu.rf.regs[2]);
        $display("  x10 = %0d  (expect 0  = counter done)", dut.dpu.rf.regs[10]);
      

        if (dut.dpu.rf.regs[1] === 32'd21 &&
            dut.dpu.rf.regs[2] === 32'd34 &&
            dut.dpu.rf.regs[10] === 32'd0)
            $display("  *** EXPECTED RESULT ARRIVED-PASS ***");
        else
            $display("  *** FAIL — check branch logic ***");

        $finish;
    end

endmodule

fibonacci_wave.vcd
$date
	Sun Jun 14 23:56:59 2026
$end
$version
	Icarus Verilog
$end
$timescale
	1ps
$end
$scope module tb_fibonacci $end
$var reg 1 ! clk $end
$var reg 1 " reset $end
$scope module dut $end
$var wire 1 ! clk $end
$var wire 1 " reset $end
$var wire 1 # sw $end
$var wire 1 $ reg_write $end
$var wire 32 % pc_plus4 [31:0] $end
$var wire 32 & pc [31:0] $end
$var wire 1 ' mem_to_reg $end
$var wire 1 ( lui_control $end
$var wire 1 ) lb $end
$var wire 1 * jump $end
$var wire 32 + instruction [31:0] $end
$var wire 32 , imm_val [31:0] $end
$var wire 1 - bneq_control $end
$var wire 1 . bneq $end
$var wire 1 / blt_control $end
$var wire 1 0 blt $end
$var wire 1 1 bgeq_control $end
$var wire 1 2 bge $end
$var wire 1 3 beq_control $end
$var wire 1 4 beq $end
$var wire 6 5 alu_control [5:0] $end
$scope module cu $end
$var wire 3 6 funct3 [2:0] $end
$var wire 7 7 funct7 [6:0] $end
$var wire 7 8 opcode [6:0] $end
$var wire 1 " reset $end
$var reg 6 9 alu_control [5:0] $end
$var reg 1 3 beq_control $end
$var reg 1 1 bgeq_control $end
$var reg 1 / blt_control $end
$var reg 1 - bneq_control $end
$var reg 1 * jump $end
$var reg 1 ) lb $end
$var reg 1 ( lui_control $end
$var reg 1 ' mem_to_reg $end
$var reg 1 $ reg_write $end
$var reg 1 # sw $end
$upscope $end
$scope module dpu $end
$var wire 6 : alu_control [5:0] $end
$var wire 1 3 beq_control $end
$var wire 1 1 bgeq_control $end
$var wire 1 / blt_control $end
$var wire 1 - bneq_control $end
$var wire 1 ! clk $end
$var wire 1 * jump $end
$var wire 1 ) lb $end
$var wire 1 ( lui_control $end
$var wire 1 ' mem_to_reg $end
$var wire 5 ; rd [4:0] $end
$var wire 1 $ reg_write $end
$var wire 5 < rs1 [4:0] $end
$var wire 5 = rs2 [4:0] $end
$var wire 1 " rst $end
$var wire 1 # sw $end
$var wire 32 > write_back_data [31:0] $end
$var wire 32 ? read_data2 [31:0] $end
$var wire 32 @ read_data1 [31:0] $end
$var wire 32 A pc_plus4 [31:0] $end
$var wire 32 B mem_rd_data [31:0] $end
$var wire 32 C imm_val [31:0] $end
$var wire 1 . bneq $end
$var wire 1 0 blt $end
$var wire 1 2 bge $end
$var wire 1 4 beq $end
$var wire 32 D alu_src2 [31:0] $end
$var wire 32 E alu_result [31:0] $end
$scope module alu_unit $end
$var wire 6 F alu_control [5:0] $end
$var wire 32 G src2 [31:0] $end
$var wire 32 H src1 [31:0] $end
$var reg 32 I result [31:0] $end
$upscope $end
$scope module dmem $end
$var wire 32 J addr [31:0] $end
$var wire 1 ! clk $end
$var wire 32 K rd_data [31:0] $end
$var wire 1 " rst $end
$var wire 1 # sw $end
$var wire 32 L wr_data [31:0] $end
$var integer 32 M i [31:0] $end
$upscope $end
$scope module rf $end
$var wire 1 ! clk $end
$var wire 5 N rd [4:0] $end
$var wire 1 $ reg_write $end
$var wire 5 O rs1 [4:0] $end
$var wire 5 P rs2 [4:0] $end
$var wire 1 " rst $end
$var wire 32 Q write_data [31:0] $end
$var wire 32 R read_data2 [31:0] $end
$var wire 32 S read_data1 [31:0] $end
$var integer 32 T i [31:0] $end
$upscope $end
$upscope $end
$scope module ifu $end
$var wire 1 4 beq $end
$var wire 1 2 bge $end
$var wire 1 0 blt $end
$var wire 1 . bneq $end
$var wire 1 ! clk $end
$var wire 1 * jump $end
$var wire 1 " reset $end
$var wire 32 U imm_jump [31:0] $end
$var wire 32 V imm_branch [31:0] $end
$var reg 32 W pc [31:0] $end
$var reg 32 X pc_plus4 [31:0] $end
$upscope $end
$scope module ig $end
$var wire 7 Y opcode [6:0] $end
$var wire 32 Z instr [31:0] $end
$var reg 32 [ imm_out [31:0] $end
$upscope $end
$scope module imem $end
$var wire 32 \ instruction [31:0] $end
$var wire 32 ] pc [31:0] $end
$scope begin fill $end
$var integer 32 ^ i [31:0] $end
$upscope $end
$upscope $end
$upscope $end
$upscope $end
$scope module tb_fibonacci $end
$scope module dut $end
$scope module dpu $end
$scope module rf $end
$var reg 32 _ \regs[0] [31:0] $end
$upscope $end
$upscope $end
$upscope $end
$upscope $end
$scope module tb_fibonacci $end
$scope module dut $end
$scope module dpu $end
$scope module rf $end
$var reg 32 ` \regs[1] [31:0] $end
$upscope $end
$upscope $end
$upscope $end
$upscope $end
$scope module tb_fibonacci $end
$scope module dut $end
$scope module dpu $end
$scope module rf $end
$var reg 32 a \regs[2] [31:0] $end
$upscope $end
$upscope $end
$upscope $end
$upscope $end
$scope module tb_fibonacci $end
$scope module dut $end
$scope module dpu $end
$scope module rf $end
$var reg 32 b \regs[3] [31:0] $end
$upscope $end
$upscope $end
$upscope $end
$upscope $end
$scope module tb_fibonacci $end
$scope module dut $end
$scope module dpu $end
$scope module rf $end
$var reg 32 c \regs[10] [31:0] $end
$upscope $end
$upscope $end
$upscope $end
$upscope $end
$enddefinitions $end
$comment Show the parameter values. $end
$dumpall
$end
#0
$dumpvars
b0 c
b0 b
b0 a
b0 `
b0 _
b100000000 ^
bx ]
bx \
bx [
bx Z
bx Y
bx X
bx W
bx V
bx U
b100000 T
bx S
bx R
b0 Q
bx P
bx O
bx N
bx M
bx L
bx K
b0 J
b0 I
bx H
bx G
b0 F
b0 E
bx D
bx C
bx B
bx A
bx @
bx ?
b0 >
bx =
bx <
bx ;
b0 :
b0 9
bx 8
bx 7
bx 6
b0 5
04
03
02
01
00
0/
0.
0-
bx ,
bx +
0*
0)
0(
0'
bx &
bx %
0$
0#
1"
0!
$end
#5000
b0 ?
b0 L
b0 R
b0 @
b0 H
b0 S
b0 D
b0 G
b10011 Y
b1 ;
b1 N
b0 =
b0 P
b0 <
b0 O
b10011 8
b0 6
b0 7
b0 ,
b0 C
b0 U
b0 V
b0 [
b10010011 +
b10010011 Z
b10010011 \
b0 %
b0 A
b0 X
b0 &
b0 W
b0 ]
b0 B
b0 K
b100000000 M
1!
#10000
b0 c
b0 b
b0 a
b0 `
b0 _
b100000 T
0!
#15000
b100000000 M
1!
#16000
b1011 5
b1011 9
b1011 :
b1011 F
1$
0"
#20000
b0 `
0!
#25000
b1 >
b1 Q
b1 E
b1 I
b1 J
b1 D
b1 G
b10 ;
b10 N
b1 =
b1 P
b1 ,
b1 C
b1 U
b1 V
b1 [
b100000000000100010011 +
b100000000000100010011 Z
b100000000000100010011 \
b100 &
b100 W
b100 ]
b100 %
b100 A
b100 X
1!
#30000
b1 a
0!
#35000
b1000 >
b1000 Q
b1000 E
b1000 I
b1000 J
b1000 D
b1000 G
b1010 ;
b1010 N
b1000 =
b1000 P
b1000 ,
b1000 C
b1000 U
b1000 V
b1000 [
b100000000000010100010011 +
b100000000000010100010011 Z
b100000000000010100010011 \
b1000 &
b1000 W
b1000 ]
b1000 %
b1000 A
b1000 X
1!
#40000
b1000 c
0!
#45000
b1 >
b1 Q
b1 E
b1 I
b1 J
b1 ?
b1 L
b1 R
1$
b1 5
b1 9
b1 :
b1 F
b1 D
b1 G
b110011 Y
b11 ;
b11 N
b10 =
b10 P
b1 <
b1 O
b110011 8
b0 ,
b0 C
b0 U
b0 V
b0 [
b1000001000000110110011 +
b1000001000000110110011 Z
b1000001000000110110011 \
b1100 &
b1100 W
b1100 ]
b1100 %
b1100 A
b1100 X
1!
#50000
b1 b
0!
#55000
b1 >
b1 Q
b0 D
b0 G
b1 E
b1 I
b1 J
b0 ?
b0 L
b0 R
b1 @
b1 H
b1 S
1$
b1011 5
b1011 9
b1011 :
b1011 F
b10011 Y
b1 ;
b1 N
b0 =
b0 P
b10 <
b10 O
b10011 8
b10000000010010011 +
b10000000010010011 Z
b10000000010010011 \
b10000 &
b10000 W
b10000 ]
b10000 %
b10000 A
b10000 X
1!
#60000
b1 `
0!
#65000
b10 ;
b10 N
b11 <
b11 O
b11000000100010011 +
b11000000100010011 Z
b11000000100010011 \
b10100 &
b10100 W
b10100 ]
b10100 %
b10100 A
b10100 X
1!
#70000
b1 a
0!
#75000
b111 >
b111 Q
b111 E
b111 I
b111 J
b1000 @
b1000 H
b1000 S
1$
b1011 5
b1011 9
b1011 :
b1011 F
b11111111111111111111111111111111 D
b11111111111111111111111111111111 G
b1010 ;
b1010 N
b11111 =
b11111 P
b1010 <
b1010 O
b1111111 7
b11111111111111111111111111111111 ,
b11111111111111111111111111111111 C
b11111111111111111111111111111111 U
b11111111111111111111111111111111 V
b11111111111111111111111111111111 [
b11111111111101010000010100010011 +
b11111111111101010000010100010011 Z
b11111111111101010000010100010011 \
b11000 &
b11000 W
b11000 ]
b11000 %
b11000 A
b11000 X
1!
#80000
b110 >
b110 Q
b110 E
b110 I
b110 J
b111 @
b111 H
b111 S
b111 c
0!
#85000
b1 >
b1 Q
1.
b1 E
b1 I
b1 J
1-
0$
b11101 5
b11101 9
b11101 :
b11101 F
b0 D
b0 G
b1100011 Y
b10001 ;
b10001 N
b0 =
b0 P
b1100011 8
b1 6
b11111111111111111111111111110000 ,
b11111111111111111111111111110000 C
b11111111111111111111111111110000 U
b11111111111111111111111111110000 V
b11111111111111111111111111110000 [
b11111110000001010001100011100011 +
b11111110000001010001100011100011 Z
b11111110000001010001100011100011 \
b11100 &
b11100 W
b11100 ]
b11100 %
b11100 A
b11100 X
1!
#90000
0!
#95000
b10 >
b10 Q
b10 E
b10 I
b10 J
0.
b1 D
b1 G
b1 ?
b1 L
b1 R
b1 @
b1 H
b1 S
1$
0-
b1 5
b1 9
b1 :
b1 F
b110011 Y
b11 ;
b11 N
b10 =
b10 P
b1 <
b1 O
b110011 8
b0 6
b0 7
b0 ,
b0 C
b0 U
b0 V
b0 [
b1000001000000110110011 +
b1000001000000110110011 Z
b1000001000000110110011 \
b1100 &
b1100 W
b1100 ]
b100000 %
b100000 A
b100000 X
1!
#100000
b10 b
0!
#105000
b1 >
b1 Q
b1 E
b1 I
b1 J
b0 D
b0 G
b0 ?
b0 L
b0 R
1$
b1011 5
b1011 9
b1011 :
b1011 F
b10011 Y
b1 ;
b1 N
b0 =
b0 P
b10 <
b10 O
b10011 8
b10000000010010011 +
b10000000010010011 Z
b10000000010010011 \
b10000 &
b10000 W
b10000 ]
b10000 %
b10000 A
b10000 X
1!
#110000
b1 `
0!
#115000
b10 >
b10 Q
b10 E
b10 I
b10 J
b10 @
b10 H
b10 S
b10 ;
b10 N
b11 <
b11 O
b11000000100010011 +
b11000000100010011 Z
b11000000100010011 \
b10100 &
b10100 W
b10100 ]
b10100 %
b10100 A
b10100 X
1!
#120000
b10 a
0!
#125000
b110 >
b110 Q
b110 E
b110 I
b110 J
b111 @
b111 H
b111 S
1$
b1011 5
b1011 9
b1011 :
b1011 F
b11111111111111111111111111111111 D
b11111111111111111111111111111111 G
b1010 ;
b1010 N
b11111 =
b11111 P
b1010 <
b1010 O
b1111111 7
b11111111111111111111111111111111 ,
b11111111111111111111111111111111 C
b11111111111111111111111111111111 U
b11111111111111111111111111111111 V
b11111111111111111111111111111111 [
b11111111111101010000010100010011 +
b11111111111101010000010100010011 Z
b11111111111101010000010100010011 \
b11000 &
b11000 W
b11000 ]
b11000 %
b11000 A
b11000 X
1!
#130000
b101 >
b101 Q
b101 E
b101 I
b101 J
b110 @
b110 H
b110 S
b110 c
0!
#135000
b1 >
b1 Q
1.
b1 E
b1 I
b1 J
1-
0$
b11101 5
b11101 9
b11101 :
b11101 F
b0 D
b0 G
b1100011 Y
b10001 ;
b10001 N
b0 =
b0 P
b1100011 8
b1 6
b11111111111111111111111111110000 ,
b11111111111111111111111111110000 C
b11111111111111111111111111110000 U
b11111111111111111111111111110000 V
b11111111111111111111111111110000 [
b11111110000001010001100011100011 +
b11111110000001010001100011100011 Z
b11111110000001010001100011100011 \
b11100 &
b11100 W
b11100 ]
b11100 %
b11100 A
b11100 X
1!
#140000
0!
